hx711_multi/__init__.py
hx711_multi/hx711.py
hx711_multi/utils.py
hx711_multi-1.4.1.dist-info/LICENSE
hx711_multi-1.4.1.dist-info/METADATA
hx711_multi-1.4.1.dist-info/WHEEL
hx711_multi-1.4.1.dist-info/top_level.txt
hx711_multi-1.4.1.dist-info/RECORD
