Metadata-Version: 2.1
Name: hx711_multi
Version: 1.4.1
Summary: HX711 class to sample 24-bit ADCs with Python 3 on a Raspberry Pi Rasperry Pi Zero, 2 or 3
Home-page: https://github.com/Morrious/hx711-multi
Author: James Morris
Author-email: james@james.pizza
Project-URL: Bug Tracker, https://github.com/Morrious/hx711-multi/issues
Classifier: Programming Language :: Python :: 3
Classifier: License :: OSI Approved :: MIT License
Classifier: Operating System :: OS Independent
Requires-Python: >=3.6
License-File: LICENSE
